{
  "project_info": {
    "project_number": "895621837575",
    "firebase_url": "https://share-acec9.firebaseio.com",
    "project_id": "share-acec9",
    "storage_bucket": "share-acec9.appspot.com"
  },
  "client": [
    {
      "client_info": {
        "mobilesdk_app_id": "1:895621837575:android:73cfba64784336a4",
        "android_client_info": {
          "package_name": "com.ipaymyway.share"
        }
      },
      "oauth_client": [
        {
          "client_id": "895621837575-hatnvrkfh0mkm5qvrl9so1m43nuruacm.apps.googleusercontent.com",
          "client_type": 1,
          "android_info": {
            "package_name": "com.ipaymyway.share",
            "certificate_hash": "c56fbaddb2f7df615a1fbf860f618aeffe8e1157"
          }
        },
        {
          "client_id": "895621837575-isund6gm6r9t2pepcn19agnogaeh69k7.apps.googleusercontent.com",
          "client_type": 3
        }
      ],
      "api_key": [
        {
          "current_key": "AIzaSyDDKTW8c4xGAJmH5DzAaJ2zooSBQqouR7M"
        }
      ],
      "services": {
        "analytics_service": {
          "status": 1
        },
        "appinvite_service": {
          "status": 2,
          "other_platform_oauth_client": [
            {
              "client_id": "895621837575-isund6gm6r9t2pepcn19agnogaeh69k7.apps.googleusercontent.com",
              "client_type": 3
            },
            {
              "client_id": "895621837575-dfjmsiquosb7a2cdvlhbq759ji82h1aa.apps.googleusercontent.com",
              "client_type": 2,
              "ios_info": {
                "bundle_id": "com.ipaymyway.share",
                "app_store_id": "1238297051"
              }
            }
          ]
        },
        "ads_service": {
          "status": 2
        }
      }
    }
  ],
  "configuration_version": "1"
}